{
  "bacru": {
    "gloss": "utter",
    "tags": [
      "standard"
    ],
    "cmarafsi": [
      "ba'u"
    ]
  },
  "tavla": {
    "gloss": "talk",
    "tags": [
      "standard"
    ],
    "cmarafsi": [
      "tav",
      "ta'a"
    ]
  },
  "cusku": {
    "gloss": "express",
    "tags": [
      "standard"
    ],
    "cmarafsi": [
      "cus",
      "sku"
    ]
  },
  "ckule": {
    "gloss": "school",
    "tags": [
      "standard"
    ],
    "cmarafsi": [
      "kul",
      "cu'e"
    ]
  },
  "fanva": {
    "gloss": "translate",
    "tags": [
      "standard"
    ],
    "cmarafsi": []
  },
  "ckana": {
    "gloss": "bed",
    "tags": [
      "standard"
    ]
  },
  "bukpu": {
    "gloss": "cloth",
    "tags": [
      "standard"
    ]
  },
  "xamsi": {
    "gloss": "sea",
    "tags": [
      "standard"
    ]
  },
  "rirxe": {
    "gloss": "river",
    "tags": [
      "standard"
    ]
  },
  "marbi": {
    "gloss": "shelter",
    "tags": [
      "standard"
    ]
  },
  "ckunu": {
    "gloss": "conifer",
    "tags": [
      "standard"
    ]
  },
  "cukta": {
    "gloss": "book",
    "tags": [
      "standard"
    ],
    "cmarafsi": [
      "cku"
    ]
  },
  "kajna": {
    "gloss": "shelf",
    "tags": [
      "standard"
    ]
  },
  "bitmu": {
    "gloss": "wall",
    "tags": [
      "standard"
    ]
  },
  "blabi": {
    "gloss": "white",
    "tags": [
      "standard"
    ]
  },
  "cmana": {
    "gloss": "mountain",
    "tags": [
      "standard"
    ]
  },
  "sarji": {
    "gloss": "support",
    "tags": [
      "standard"
    ]
  },
  "tsani": {
    "gloss": "sky",
    "tags": [
      "standard"
    ]
  },
  "tsina": {
    "gloss": "stage",
    "tags": [
      "standard"
    ]
  },
  "draci": {
    "gloss": "play",
    "tags": [
      "standard"
    ]
  },
  "crida": {
    "gloss": "goblin",
    "tags": [
      "standard"
    ]
  },
  "bartu": {
    "gloss": "outside",
    "tags": [
      "standard"
    ]
  },
  "sligu": {
    "gloss": "solid",
    "tags": [
      "standard"
    ]
  },
  "brife": {
    "gloss": "wind",
    "tags": [
      "standard"
    ]
  },
  "snura": {
    "gloss": "safe",
    "tags": [
      "standard"
    ]
  }
}